[{   
    "_id": "1",
    "orderId": "123abc",
    "value": 120.00,
    "status":[
        {
            "name": "Pagamento aprovado",
            "createdAt": "2020-08-03 01:00:00"
        },
        {
            "name": "Aguardando pagamento",
            "createdAt": "2020-08-02 01:00:00"
        },
        {
            "name": "Pedido recebido",
            "createdAt": "2020-08-01 01:00:00"
        }
    ],
    "createdAt": "2020-08-03 01:00:00"
},
{   
    "_id": "3",
    "orderId": "456def",
    "value": 100.00,
    "status":[
        {
            "name": "Aguardando pagamento",
            "createdAt": "2020-08-03 17:48:16"
        }
    ],
    "createdAt": "2020-08-03 17:48:16"
},
{   
    "_id": "4",
    "orderId": "789eee",
    "value": 100.00,
    "status":[
        {
            "name": "Aguardando pagamento",
            "createdAt": "2020-08-04 08:55:47"
        }
    ],
    "createdAt": "2020-08-04 08:55:47"
}
]